CHANGES.txt
LICENSE
MANIFEST.in
README.rst
setup.py
whiptail.py
whiptail.egg-info/PKG-INFO
whiptail.egg-info/SOURCES.txt
whiptail.egg-info/dependency_links.txt
whiptail.egg-info/namespace_packages.txt
whiptail.egg-info/top_level.txt