Metadata-Version: 1.1
Name: whiptail
Version: 0.2
Summary: Use whiptail to display dialog boxes from shell scripts
Home-page: https://github.com/marwano/whiptail
Author: Marwan Alsabbagh
Author-email: marwan.alsabbagh@gmail.com
License: BSD
Keywords: whiptail
Platform: UNKNOWN
Classifier: Development Status :: 5 - Production/Stable
Classifier: Environment :: Console
Classifier: Intended Audience :: Developers
Classifier: License :: OSI Approved :: BSD License
Classifier: Operating System :: OS Independent
Classifier: Programming Language :: Python
Classifier: Programming Language :: Python :: 2.7
